pt6312/__init__.py
pt6312/constants.py
pt6312/font_seg13.py
pt6312/helpers.py
pt6312/pt6312.py
pt6312-0.1.1.dist-info/LICENSE
pt6312-0.1.1.dist-info/METADATA
pt6312-0.1.1.dist-info/WHEEL
pt6312-0.1.1.dist-info/top_level.txt
pt6312-0.1.1.dist-info/RECORD
